wallypub/__init__.py
wallypub/main.py
wallypub/conf/__init__.py
wallypub/conf/app.py
wallypub/conf/constants.py
wallypub/conf/font.py
wallypub/epub_builder/__init__.py
wallypub/epub_builder/create.py
wallypub/epub_builder/create_test.py
wallypub/epub_builder/formatter.py
wallypub/epub_builder/formatter_test.py
wallypub/epub_builder/from_wallabag.py
wallypub/epub_builder/from_wallabag_test.py
wallypub/epub_builder/test_input/wbag_entries_input.json
wallypub/img/__init__.py
wallypub/img/color.py
wallypub/img/color_test.py
wallypub/img/generate.py
wallypub/img/generate_test.py
wallypub/services/__init__.py
wallypub/services/readitlater.py
wallypub/services/wallabag.py
wallypub/services/wallabag_test.py
wallypub/templates/backmatter.html
wallypub/tui/__init__.py
wallypub/tui/choice_builder.py
wallypub/tui/termui.py
wallypub/tui/update_config.py
wallypub/utils/__init__.py
wallypub/utils/date.py
wallypub/utils/date_test.py
wallypub/utils/http.py
wallypub/utils/params.py
wallypub/utils/params_test.py
wallypub-1.0.1.dist-info/METADATA
wallypub-1.0.1.dist-info/WHEEL
wallypub-1.0.1.dist-info/entry_points.txt
wallypub-1.0.1.dist-info/licenses/LICENSE
wallypub-1.0.1.dist-info/RECORD
