Metadata-Version: 2.4
Name: wallypub
Version: 1.0.1
Summary: CLI Wallabag companion for generating epubs.
License-File: LICENSE
Requires-Python: >=3.10
Requires-Dist: bs4>=0.0.2
Requires-Dist: click>=8.3.1
Requires-Dist: coverage>=7.13.0
Requires-Dist: datetime>=5.5
Requires-Dist: httpie>=3.2.4
Requires-Dist: importlib>=1.0.4
Requires-Dist: inquirerpy>=0.3.4
Requires-Dist: keyring>=25.7.0
Requires-Dist: levenshtein>=0.27.3
Requires-Dist: numpy>=2.2.6
Requires-Dist: platformdirs>=4.5.1
Requires-Dist: pydantic-settings-export>=1.0.3
Requires-Dist: pydantic-settings>=2.12.0
Requires-Dist: pydantic>=2.12.5
Requires-Dist: pypub3>=2.0.9
Requires-Dist: pytest>=8.4.2
Requires-Dist: requests>=2.32.4
Requires-Dist: swaggerpy>=0.2.1
Requires-Dist: toml-dataclass>=0.1.0
Requires-Dist: toml>=0.10.2
